salamandra/__init__.py
salamandra/associable.py
salamandra/bus.py
salamandra/component.py
salamandra/componentVIRT.py
salamandra/componentXY.py
salamandra/gnet.py
salamandra/group.py
salamandra/inout.py
salamandra/input.py
salamandra/lexer.py
salamandra/net.py
salamandra/object.py
salamandra/output.py
salamandra/pin.py
salamandra/read_verilog_tech_file_to_salamandra.py
salamandra/sclib.py
salamandra/spectre2slm.py
salamandra/verilog2slm.py
salamandra-1.0.1.dist-info/LICENSE
salamandra-1.0.1.dist-info/METADATA
salamandra-1.0.1.dist-info/WHEEL
salamandra-1.0.1.dist-info/top_level.txt
salamandra-1.0.1.dist-info/RECORD
