Metadata-Version: 2.1
Name: salamandra
Version: 1.0.1
Summary: Framework for netlist manipulation
Home-page: https://github.com/enics-labs/salamandra
Author: Tzachi Noy
Author-email: tzachi.noy@biu.ac.il
License: UNKNOWN
Project-URL: EnICS Labs, https://enicslabs.com/
Platform: UNKNOWN
Classifier: Programming Language :: Python :: 3
Classifier: License :: OSI Approved :: Apache Software License
Classifier: Operating System :: OS Independent
Requires-Python: >=3.5
